README.rst
_description.org
lh-agpl3-LICENSE.txt
pyproject.toml
setup.py
bisos/__init__.py
bisos.py3_all.egg-info/PKG-INFO
bisos.py3_all.egg-info/SOURCES.txt
bisos.py3_all.egg-info/dependency_links.txt
bisos.py3_all.egg-info/not-zip-safe
bisos.py3_all.egg-info/requires.txt
bisos.py3_all.egg-info/top_level.txt
bisos/full/__init__.py