Metadata-Version: 2.2
Name: bisos.py3-all
Version: 0.14
Summary: bisos.py3-all:  Top level module -- bisos.core + bisosPkgs + adopted bisos external pkgs
Home-page: http://www.by-star.net/PLPC/180047
Download-URL: http://www.by-star.net/PLPC/180047
Author: Mohsen Banan
Author-email: libre@mohsen.1.banan.byname.net
Maintainer: Mohsen Banan
Maintainer-email: libre@mohsen.1.banan.byname.net
License: AGPL
Classifier: Development Status :: 5 - Production/Stable
Classifier: Intended Audience :: Developers
Classifier: License :: OSI Approved :: GNU Affero General Public License v3
Classifier: Operating System :: POSIX
Classifier: Programming Language :: Python
Classifier: Topic :: Software Development :: Libraries
Classifier: Topic :: Software Development :: Libraries :: Python Modules
Requires-Dist: bisos.b
Requires-Dist: bisos.common
Requires-Dist: bisos.provision
Requires-Dist: bisos.siteRegistrars
Requires-Dist: bisos.transit
Requires-Dist: blee.csPlayer
Requires-Dist: bisos.banna
Requires-Dist: bisos.usgAcct
Requires-Dist: bisos.regfps
Requires-Dist: bisos.core
Requires-Dist: bisos.lcnt
Requires-Dist: bisos.things
Requires-Dist: bisos.gossonot
Requires-Dist: bisos.icm
Requires-Dist: bisos.basics
Requires-Dist: bisos.bpo
Requires-Dist: bisos.cntnr
Requires-Dist: bisos.currents
Requires-Dist: bisos.pals
Requires-Dist: bisos.binsprep
Requires-Dist: bisos.capability
Dynamic: author
Dynamic: author-email
Dynamic: classifier
Dynamic: description
Dynamic: download-url
Dynamic: home-page
Dynamic: license
Dynamic: maintainer
Dynamic: maintainer-email
Dynamic: requires-dist
Dynamic: summary
